LICENSE
README.md
setup.py
schneiders.egg-info/PKG-INFO
schneiders.egg-info/SOURCES.txt
schneiders.egg-info/dependency_links.txt
schneiders.egg-info/requires.txt
schneiders.egg-info/top_level.txt
schneiders_V0/__init__.py
schneiders_V0/mosquito.py